{
  "preparations": [
    {
      "id": 1747387004787,
      "items": [
        {
          "name": "Menu Mitraillette Classique",
          "quantity": 1,
          "relatedItems": [
            "Salade",
            "Tomate",
            "Oignons Frit",
            "Frites"
          ]
        },
        {
          "relatedItems": [
            "Lucifer"
          ]
        },
        {
          "relatedItems": [
            "Dallas"
          ]
        },
        {
          "quantity": 1,
          "relatedItems": [
            "Maroille"
          ]
        },
        {
          "name": "",
          "quantity": 1,
          "relatedItems": [
            "Leffe Ruby"
          ]
        },
        {
          "name": "Party Box",
          "quantity": 1,
          "relatedItems": []
        },
        {
          "quantity": 1,
          "relatedItems": [
            "Andalouse"
          ]
        },
        {
          "name": "",
          "quantity": 1,
          "relatedItems": []
        }
      ],
      "user_name": "Nadege",
      "user_phone": "0606060606",
      "user_image": "/avatar.jpg",
      "time": "19h",
      "date": "2025-05-16T10:21:36.517Z",
      "lieu": "Maison",
      "price": "25.5€",
      "createdAt": "2025-05-16T09:16:44.787Z"
    },
    {
      "id": 1747394063238,
      "items": [],
      "user_name": "enola",
      "user_phone": "0606060606",
      "user_image": "/avatar.jpg",
      "time": "18h45",
      "date": "2025-05-16T12:10:11.134Z",
      "lieu": "Maison",
      "price": "0€",
      "createdAt": "2025-05-16T11:14:23.238Z"
    },
    {
      "id": 1747394103755,
      "items": [
        {
          "name": "Menu Enfants",
          "quantity": 1,
          "relatedItems": [
            "Creme au chocolat",
            "Poulycroc"
          ]
        },
        {
          "relatedItems": [
            "Hannibale"
          ]
        }
      ],
      "user_name": "enola",
      "user_phone": "0606060606",
      "user_image": "/avatar.jpg",
      "time": "18h45",
      "date": "2025-05-16T12:10:49.382Z",
      "lieu": "Maison",
      "price": "6.5€",
      "createdAt": "2025-05-16T11:15:03.755Z"
    },
    {
      "id": 1747394247384,
      "items": [
        {
          "name": "Menu Enfants",
          "quantity": 1,
          "relatedItems": [
            "Compote",
            "Nuggets"
          ]
        },
        {
          "relatedItems": [
            "Hamburger"
          ]
        }
      ],
      "user_name": "Antony",
      "user_phone": "0606060606",
      "user_image": "/avatar.jpg",
      "time": "19h15",
      "date": "2025-05-16T12:13:01.600Z",
      "lieu": "Maison",
      "price": "6.5€",
      "createdAt": "2025-05-16T11:17:27.384Z"
    },
    {
      "id": 1747394565966,
      "items": [
        {
          "name": "Menu Enfants",
          "quantity": 1,
          "relatedItems": [
            "Compote",
            "Poulycroc"
          ]
        },
        {
          "relatedItems": [
            "Poivre"
          ]
        }
      ],
      "user_name": "cecile",
      "user_phone": "0606060606",
      "user_image": "/avatar.jpg",
      "time": "20h",
      "date": "2025-05-16T12:17:56.058Z",
      "lieu": "Maison",
      "price": "6.5€",
      "createdAt": "2025-05-16T11:22:45.966Z"
    },
    {
      "id": 1747394654945,
      "items": [
        {
          "name": "Mitraillette Classique",
          "quantity": 1,
          "relatedItems": [
            "Salade",
            "Tomate",
            "Oignons Frit"
          ]
        },
        {
          "relatedItems": [
            "Poulycroc"
          ]
        },
        {
          "relatedItems": [
            "Brazil"
          ]
        },
        {
          "quantity": 1,
          "relatedItems": [
            "Aucuns supplements"
          ]
        },
        {
          "name": "Aucune boisson",
          "quantity": 1,
          "relatedItems": []
        }
      ],
      "user_name": "momo",
      "user_phone": "0606060606",
      "user_image": "/avatar.jpg",
      "time": "19h30",
      "date": "2025-05-16T12:19:18.202Z",
      "lieu": "Maison",
      "price": "6.5€",
      "createdAt": "2025-05-16T11:24:14.945Z"
    },
    {
      "id": 1747394873931,
      "items": [
        {
          "name": "Mexicano Burger",
          "quantity": 1,
          "relatedItems": [
            "Salade",
            "Tomate",
            "Cornichons sucrées",
            "Sauce Bicky"
          ]
        },
        {
          "quantity": 1,
          "relatedItems": [
            "Aucuns supplements"
          ]
        },
        {
          "name": "Leffe Ruby",
          "quantity": 1,
          "relatedItems": []
        }
      ],
      "user_name": "keke",
      "user_phone": "0606060606",
      "user_image": "/avatar.jpg",
      "time": "20h45",
      "date": "2025-05-16T12:22:40.322Z",
      "lieu": "Maison",
      "price": "11€",
      "createdAt": "2025-05-16T11:27:53.931Z"
    },
    {
      "id": 1747395139059,
      "items": [
        {
          "name": "Veggie Burger",
          "quantity": 1,
          "relatedItems": [
            "Tomate",
            "Oignons Frit",
            "Sauce Hamburger"
          ]
        },
        {
          "quantity": 1,
          "relatedItems": []
        },
        {
          "name": "Aucune boisson",
          "quantity": 1,
          "relatedItems": []
        },
        {
          "name": "",
          "quantity": 1,
          "relatedItems": []
        }
      ],
      "user_name": "juju",
      "user_phone": "0606060606",
      "user_image": "/avatar.jpg",
      "time": "21h",
      "date": "2025-05-16T12:26:45.074Z",
      "lieu": "Maison",
      "price": "7.5€",
      "createdAt": "2025-05-16T11:32:19.059Z"
    },
    {
      "id": 1747395257620,
      "items": [
        {
          "name": "Cheese Box",
          "quantity": 1,
          "relatedItems": []
        },
        {
          "name": "Party Box",
          "quantity": 1,
          "relatedItems": []
        },
        {
          "quantity": 1,
          "relatedItems": [
            "Pita"
          ]
        },
        {
          "quantity": 1,
          "relatedItems": [
            "Brazil"
          ]
        },
        {
          "quantity": 1,
          "relatedItems": [
            "Hannibale"
          ]
        }
      ],
      "user_name": "maxine",
      "user_phone": "0606060606",
      "user_image": "/avatar.jpg",
      "time": "20h30",
      "date": "2025-05-16T12:28:34.144Z",
      "lieu": "Maison",
      "price": "17.5€",
      "createdAt": "2025-05-16T11:34:17.620Z"
    },
    {
      "id": 1747395399029,
      "items": [
        {
          "name": "Tzigane",
          "quantity": 1,
          "relatedItems": []
        },
        {
          "name": "Ardennaise",
          "quantity": 1,
          "relatedItems": []
        }
      ],
      "user_name": "odile",
      "user_phone": "0606060606",
      "user_image": "/avatar.jpg",
      "time": "20h15",
      "date": "2025-05-16T12:30:44.361Z",
      "lieu": "Maison",
      "price": "10€",
      "createdAt": "2025-05-16T11:36:39.029Z"
    },
    {
      "id": 1747396257493,
      "items": [
        {
          "name": "Grandes frites",
          "quantity": 1,
          "relatedItems": []
        },
        {
          "quantity": 1,
          "relatedItems": [
            "Mayonnaise"
          ]
        },
        {
          "quantity": 1,
          "relatedItems": [
            "Samourai"
          ]
        }
      ],
      "user_name": "gg",
      "user_phone": "0606060606",
      "user_image": "/avatar.jpg",
      "time": "21h",
      "date": "2025-05-16T12:43:56.762Z",
      "lieu": "Maison",
      "price": "5.5€",
      "createdAt": "2025-05-16T11:50:57.493Z"
    },
    {
      "id": 1747396335432,
      "items": [
        {
          "name": "Ardennaise",
          "quantity": 5,
          "relatedItems": []
        },
        {
          "name": "",
          "quantity": 1,
          "relatedItems": []
        }
      ],
      "user_name": "fred",
      "user_phone": "0606060606",
      "user_image": "/avatar.jpg",
      "time": "21h15",
      "date": "2025-05-16T12:45:09.420Z",
      "lieu": "Maison",
      "price": "25€",
      "createdAt": "2025-05-16T11:52:15.432Z"
    }
  ],
  "pretes": [
    {
      "id": 1747128238365,
      "items": [
        {
          "name": "Menu Enfants",
          "quantity": 1,
          "relatedItems": [
            "Creme au chocolat",
            "Poulycroc"
          ]
        },
        {
          "relatedItems": [
            "Ketchup"
          ]
        }
      ],
      "user_name": "enola",
      "user_phone": "0688570630",
      "user_image": "/avatar.jpg",
      "time": "19h30",
      "date": "2025-05-13T09:23:58.351Z",
      "lieu": "Maison",
      "price": "6.5€",
      "createdAt": "2025-05-13T09:23:58.366Z"
    }
  ]
}